Metadata-Version: 2.1
Name: pycbzhelper
Version: 3.1.2
Summary: Python library for creating CBZ files with metadata.
Home-page: https://github.com/hyugogirubato/pycbzhelper
Author: hyugogirubato
Author-email: hyugogirubato@gmail.com
License: GPL-3.0-only
Keywords: metadata,manga,comics,ebooks,cbz
Classifier: Development Status :: 5 - Production/Stable
Classifier: Intended Audience :: Developers
Classifier: Intended Audience :: End Users/Desktop
Classifier: Natural Language :: English
Classifier: Operating System :: OS Independent
Classifier: Programming Language :: Python :: 3
Classifier: Programming Language :: Python :: 3.7
Classifier: Programming Language :: Python :: 3.8
Classifier: Programming Language :: Python :: 3.9
Classifier: Programming Language :: Python :: 3.10
Classifier: Topic :: Utilities
Requires-Python: >=3.7
License-File: LICENSE
